rtl/baud_gen.sv
module baud_gen #(
    parameter int CLK_FREQ_HZ = 50_000_000,
    parameter int BAUD_RATE   = 115_200
) (
    input  logic clk,
    input  logic rst_n,
    output logic baud_tick
);

    localparam int DIVISOR = CLK_FREQ_HZ / BAUD_RATE;
    localparam int CNT_W   = (DIVISOR <= 1) ? 1 : $clog2(DIVISOR);
    localparam logic [CNT_W-1:0] DIVISOR_M1 = CNT_W'(DIVISOR - 1);    

    logic [CNT_W-1:0] count;

    always_ff @(posedge clk or negedge rst_n) begin
        if (!rst_n) begin
            count     <= '0;
            baud_tick <= 1'b0;
        end else begin
            if (count == DIVISOR_M1) begin
                baud_tick <= 1'b1;
                count     <= '0;
            end else begin
                count     <= count + 1'b1;
                baud_tick <= 1'b0;
            end
        end
    end

endmodule

tb/tb_baud_gen.sv
module tb_baud_gen;

    parameter int CLK_FREQ_HZ = 50_000_000;
    parameter int BAUD_RATE   = 115_200;

    logic clk;
    logic rst_n;
    logic baud_tick;

    baud_gen #(
        .CLK_FREQ_HZ(CLK_FREQ_HZ),
        .BAUD_RATE(BAUD_RATE)
    ) dut (
        .clk(clk),
        .rst_n(rst_n),
        .baud_tick(baud_tick)
    );

    initial begin
        clk = 1'b0;
        forever #1 clk = ~clk;
    end

    initial begin
        $dumpfile("tb_baud_gen.vcd");
        $dumpvars(0, tb_baud_gen);

        rst_n = 1'b0;
        repeat (3) @(posedge clk);
        rst_n = 1'b1;

        repeat (600) @(posedge clk);
        $finish;
    end

endmodule

tb_baud_gen.vcd
$version Generated by VerilatedVcd $end
$timescale 1ps $end
 $scope module TOP $end
  $scope module tb_baud_gen $end
   $var wire 32 ' CLK_FREQ_HZ [31:0] $end
   $var wire 32 ( BAUD_RATE [31:0] $end
   $var wire 1 # clk $end
   $var wire 1 $ rst_n $end
   $var wire 1 % baud_tick $end
   $scope module dut $end
    $var wire 32 ' CLK_FREQ_HZ [31:0] $end
    $var wire 32 ( BAUD_RATE [31:0] $end
    $var wire 1 # clk $end
    $var wire 1 $ rst_n $end
    $var wire 1 % baud_tick $end
    $var wire 32 ) DIVISOR [31:0] $end
    $var wire 32 * CNT_W [31:0] $end
    $var wire 9 + DIVISOR_M1 [8:0] $end
    $var wire 9 & count [8:0] $end
   $upscope $end
  $upscope $end
 $upscope $end
$enddefinitions $end


#0
0#
0$
0%
b000000000 &
b00000010111110101111000010000000 '
b00000000000000011100001000000000 (
b00000000000000000000000110110010 )
b00000000000000000000000000001001 *
b110110001 +
#1
1#
#2
0#
#3
1#
#4
0#
#5
1#
1$
b000000001 &
#6
0#
#7
1#
b000000010 &
#8
0#
#9
1#
b000000011 &
#10
0#
#11
1#
b000000100 &
#12
0#
#13
1#
b000000101 &
#14
0#
#15
1#
b000000110 &
#16
0#
#17
1#
b000000111 &
#18
0#
#19
1#
b000001000 &
#20
0#
#21
1#
b000001001 &
#22
0#
#23
1#
b000001010 &
#24
0#
#25
1#
b000001011 &
#26
0#
#27
1#
b000001100 &
#28
0#
#29
1#
b000001101 &
#30
0#
#31
1#
b000001110 &
#32
0#
#33
1#
b000001111 &
#34
0#
#35
1#
b000010000 &
#36
0#
#37
1#
b000010001 &
#38
0#
#39
1#
b000010010 &
#40
0#
#41
1#
b000010011 &
#42
0#
#43
1#
b000010100 &
#44
0#
#45
1#
b000010101 &
#46
0#
#47
1#
b000010110 &
#48
0#
#49
1#
b000010111 &
#50
0#
#51
1#
b000011000 &
#52
0#
#53
1#
b000011001 &
#54
0#
#55
1#
b000011010 &
#56
0#
#57
1#
b000011011 &
#58
0#
#59
1#
b000011100 &
#60
0#
#61
1#
b000011101 &
#62
0#
#63
1#
b000011110 &
#64
0#
#65
1#
b000011111 &
#66
0#
#67
1#
b000100000 &
#68
0#
#69
1#
b000100001 &
#70
0#
#71
1#
b000100010 &
#72
0#
#73
1#
b000100011 &
#74
0#
#75
1#
b000100100 &
#76
0#
#77
1#
b000100101 &
#78
0#
#79
1#
b000100110 &
#80
0#
#81
1#
b000100111 &
#82
0#
#83
1#
b000101000 &
#84
0#
#85
1#
b000101001 &
#86
0#
#87
1#
b000101010 &
#88
0#
#89
1#
b000101011 &
#90
0#
#91
1#
b000101100 &
#92
0#
#93
1#
b000101101 &
#94
0#
#95
1#
b000101110 &
#96
0#
#97
1#
b000101111 &
#98
0#
#99
1#
b000110000 &
#100
0#
#101
1#
b000110001 &
#102
0#
#103
1#
b000110010 &
#104
0#
#105
1#
b000110011 &
#106
0#
#107
1#
b000110100 &
#108
0#
#109
1#
b000110101 &
#110
0#
#111
1#
b000110110 &
#112
0#
#113
1#
b000110111 &
#114
0#
#115
1#
b000111000 &
#116
0#
#117
1#
b000111001 &
#118
0#
#119
1#
b000111010 &
#120
0#
#121
1#
b000111011 &
#122
0#
#123
1#
b000111100 &
#124
0#
#125
1#
b000111101 &
#126
0#
#127
1#
b000111110 &
#128
0#
#129
1#
b000111111 &
#130
0#
#131
1#
b001000000 &
#132
0#
#133
1#
b001000001 &
#134
0#
#135
1#
b001000010 &
#136
0#
#137
1#
b001000011 &
#138
0#
#139
1#
b001000100 &
#140
0#
#141
1#
b001000101 &
#142
0#
#143
1#
b001000110 &
#144
0#
#145
1#
b001000111 &
#146
0#
#147
1#
b001001000 &
#148
0#
#149
1#
b001001001 &
#150
0#
#151
1#
b001001010 &
#152
0#
#153
1#
b001001011 &
#154
0#
#155
1#
b001001100 &
#156
0#
#157
1#
b001001101 &
#158
0#
#159
1#
b001001110 &
#160
0#
#161
1#
b001001111 &
#162
0#
#163
1#
b001010000 &
#164
0#
#165
1#
b001010001 &
#166
0#
#167
1#
b001010010 &
#168
0#
#169
1#
b001010011 &
#170
0#
#171
1#
b001010100 &
#172
0#
#173
1#
b001010101 &
#174
0#
#175
1#
b001010110 &
#176
0#
#177
1#
b001010111 &
#178
0#
#179
1#
b001011000 &
#180
0#
#181
1#
b001011001 &
#182
0#
#183
1#
b001011010 &
#184
0#
#185
1#
b001011011 &
#186
0#
#187
1#
b001011100 &
#188
0#
#189
1#
b001011101 &
#190
0#
#191
1#
b001011110 &
#192
0#
#193
1#
b001011111 &
#194
0#
#195
1#
b001100000 &
#196
0#
#197
1#
b001100001 &
#198
0#
#199
1#
b001100010 &
#200
0#
#201
1#
b001100011 &
#202
0#
#203
1#
b001100100 &
#204
0#
#205
1#
b001100101 &
#206
0#
#207
1#
b001100110 &
#208
0#
#209
1#
b001100111 &
#210
0#
#211
1#
b001101000 &
#212
0#
#213
1#
b001101001 &
#214
0#
#215
1#
b001101010 &
#216
0#
#217
1#
b001101011 &
#218
0#
#219
1#
b001101100 &
#220
0#
#221
1#
b001101101 &
#222
0#
#223
1#
b001101110 &
#224
0#
#225
1#
b001101111 &
#226
0#
#227
1#
b001110000 &
#228
0#
#229
1#
b001110001 &
#230
0#
#231
1#
b001110010 &
#232
0#
#233
1#
b001110011 &
#234
0#
#235
1#
b001110100 &
#236
0#
#237
1#
b001110101 &
#238
0#
#239
1#
b001110110 &
#240
0#
#241
1#
b001110111 &
#242
0#
#243
1#
b001111000 &
#244
0#
#245
1#
b001111001 &
#246
0#
#247
1#
b001111010 &
#248
0#
#249
1#
b001111011 &
#250
0#
#251
1#
b001111100 &
#252
0#
#253
1#
b001111101 &
#254
0#
#255
1#
b001111110 &
#256
0#
#257
1#
b001111111 &
#258
0#
#259
1#
b010000000 &
#260
0#
#261
1#
b010000001 &
#262
0#
#263
1#
b010000010 &
#264
0#
#265
1#
b010000011 &
#266
0#
#267
1#
b010000100 &
#268
0#
#269
1#
b010000101 &
#270
0#
#271
1#
b010000110 &
#272
0#
#273
1#
b010000111 &
#274
0#
#275
1#
b010001000 &
#276
0#
#277
1#
b010001001 &
#278
0#
#279
1#
b010001010 &
#280
0#
#281
1#
b010001011 &
#282
0#
#283
1#
b010001100 &
#284
0#
#285
1#
b010001101 &
#286
0#
#287
1#
b010001110 &
#288
0#
#289
1#
b010001111 &
#290
0#
#291
1#
b010010000 &
#292
0#
#293
1#
b010010001 &
#294
0#
#295
1#
b010010010 &
#296
0#
#297
1#
b010010011 &
#298
0#
#299
1#
b010010100 &
#300
0#
#301
1#
b010010101 &
#302
0#
#303
1#
b010010110 &
#304
0#
#305
1#
b010010111 &
#306
0#
#307
1#
b010011000 &
#308
0#
#309
1#
b010011001 &
#310
0#
#311
1#
b010011010 &
#312
0#
#313
1#
b010011011 &
#314
0#
#315
1#
b010011100 &
#316
0#
#317
1#
b010011101 &
#318
0#
#319
1#
b010011110 &
#320
0#
#321
1#
b010011111 &
#322
0#
#323
1#
b010100000 &
#324
0#
#325
1#
b010100001 &
#326
0#
#327
1#
b010100010 &
#328
0#
#329
1#
b010100011 &
#330
0#
#331
1#
b010100100 &
#332
0#
#333
1#
b010100101 &
#334
0#
#335
1#
b010100110 &
#336
0#
#337
1#
b010100111 &
#338
0#
#339
1#
b010101000 &
#340
0#
#341
1#
b010101001 &
#342
0#
#343
1#
b010101010 &
#344
0#
#345
1#
b010101011 &
#346
0#
#347
1#
b010101100 &
#348
0#
#349
1#
b010101101 &
#350
0#
#351
1#
b010101110 &
#352
0#
#353
1#
b010101111 &
#354
0#
#355
1#
b010110000 &
#356
0#
#357
1#
b010110001 &
#358
0#
#359
1#
b010110010 &
#360
0#
#361
1#
b010110011 &
#362
0#
#363
1#
b010110100 &
#364
0#
#365
1#
b010110101 &
#366
0#
#367
1#
b010110110 &
#368
0#
#369
1#
b010110111 &
#370
0#
#371
1#
b010111000 &
#372
0#
#373
1#
b010111001 &
#374
0#
#375
1#
b010111010 &
#376
0#
#377
1#
b010111011 &
#378
0#
#379
1#
b010111100 &
#380
0#
#381
1#
b010111101 &
#382
0#
#383
1#
b010111110 &
#384
0#
#385
1#
b010111111 &
#386
0#
#387
1#
b011000000 &
#388
0#
#389
1#
b011000001 &
#390
0#
#391
1#
b011000010 &
#392
0#
#393
1#
b011000011 &
#394
0#
#395
1#
b011000100 &
#396
0#
#397
1#
b011000101 &
#398
0#
#399
1#
b011000110 &
#400
0#
#401
1#
b011000111 &
#402
0#
#403
1#
b011001000 &
#404
0#
#405
1#
b011001001 &
#406
0#
#407
1#
b011001010 &
#408
0#
#409
1#
b011001011 &
#410
0#
#411
1#
b011001100 &
#412
0#
#413
1#
b011001101 &
#414
0#
#415
1#
b011001110 &
#416
0#
#417
1#
b011001111 &
#418
0#
#419
1#
b011010000 &
#420
0#
#421
1#
b011010001 &
#422
0#
#423
1#
b011010010 &
#424
0#
#425
1#
b011010011 &
#426
0#
#427
1#
b011010100 &
#428
0#
#429
1#
b011010101 &
#430
0#
#431
1#
b011010110 &
#432
0#
#433
1#
b011010111 &
#434
0#
#435
1#
b011011000 &
#436
0#
#437
1#
b011011001 &
#438
0#
#439
1#
b011011010 &
#440
0#
#441
1#
b011011011 &
#442
0#
#443
1#
b011011100 &
#444
0#
#445
1#
b011011101 &
#446
0#
#447
1#
b011011110 &
#448
0#
#449
1#
b011011111 &
#450
0#
#451
1#
b011100000 &
#452
0#
#453
1#
b011100001 &
#454
0#
#455
1#
b011100010 &
#456
0#
#457
1#
b011100011 &
#458
0#
#459
1#
b011100100 &
#460
0#
#461
1#
b011100101 &
#462
0#
#463
1#
b011100110 &
#464
0#
#465
1#
b011100111 &
#466
0#
#467
1#
b011101000 &
#468
0#
#469
1#
b011101001 &
#470
0#
#471
1#
b011101010 &
#472
0#
#473
1#
b011101011 &
#474
0#
#475
1#
b011101100 &
#476
0#
#477
1#
b011101101 &
#478
0#
#479
1#
b011101110 &
#480
0#
#481
1#
b011101111 &
#482
0#
#483
1#
b011110000 &
#484
0#
#485
1#
b011110001 &
#486
0#
#487
1#
b011110010 &
#488
0#
#489
1#
b011110011 &
#490
0#
#491
1#
b011110100 &
#492
0#
#493
1#
b011110101 &
#494
0#
#495
1#
b011110110 &
#496
0#
#497
1#
b011110111 &
#498
0#
#499
1#
b011111000 &
#500
0#
#501
1#
b011111001 &
#502
0#
#503
1#
b011111010 &
#504
0#
#505
1#
b011111011 &
#506
0#
#507
1#
b011111100 &
#508
0#
#509
1#
b011111101 &
#510
0#
#511
1#
b011111110 &
#512
0#
#513
1#
b011111111 &
#514
0#
#515
1#
b100000000 &
#516
0#
#517
1#
b100000001 &
#518
0#
#519
1#
b100000010 &
#520
0#
#521
1#
b100000011 &
#522
0#
#523
1#
b100000100 &
#524
0#
#525
1#
b100000101 &
#526
0#
#527
1#
b100000110 &
#528
0#
#529
1#
b100000111 &
#530
0#
#531
1#
b100001000 &
#532
0#
#533
1#
b100001001 &
#534
0#
#535
1#
b100001010 &
#536
0#
#537
1#
b100001011 &
#538
0#
#539
1#
b100001100 &
#540
0#
#541
1#
b100001101 &
#542
0#
#543
1#
b100001110 &
#544
0#
#545
1#
b100001111 &
#546
0#
#547
1#
b100010000 &
#548
0#
#549
1#
b100010001 &
#550
0#
#551
1#
b100010010 &
#552
0#
#553
1#
b100010011 &
#554
0#
#555
1#
b100010100 &
#556
0#
#557
1#
b100010101 &
#558
0#
#559
1#
b100010110 &
#560
0#
#561
1#
b100010111 &
#562
0#
#563
1#
b100011000 &
#564
0#
#565
1#
b100011001 &
#566
0#
#567
1#
b100011010 &
#568
0#
#569
1#
b100011011 &
#570
0#
#571
1#
b100011100 &
#572
0#
#573
1#
b100011101 &
#574
0#
#575
1#
b100011110 &
#576
0#
#577
1#
b100011111 &
#578
0#
#579
1#
b100100000 &
#580
0#
#581
1#
b100100001 &
#582
0#
#583
1#
b100100010 &
#584
0#
#585
1#
b100100011 &
#586
0#
#587
1#
b100100100 &
#588
0#
#589
1#
b100100101 &
#590
0#
#591
1#
b100100110 &
#592
0#
#593
1#
b100100111 &
#594
0#
#595
1#
b100101000 &
#596
0#
#597
1#
b100101001 &
#598
0#
#599
1#
b100101010 &
#600
0#
#601
1#
b100101011 &
#602
0#
#603
1#
b100101100 &
#604
0#
#605
1#
b100101101 &
#606
0#
#607
1#
b100101110 &
#608
0#
#609
1#
b100101111 &
#610
0#
#611
1#
b100110000 &
#612
0#
#613
1#
b100110001 &
#614
0#
#615
1#
b100110010 &
#616
0#
#617
1#
b100110011 &
#618
0#
#619
1#
b100110100 &
#620
0#
#621
1#
b100110101 &
#622
0#
#623
1#
b100110110 &
#624
0#
#625
1#
b100110111 &
#626
0#
#627
1#
b100111000 &
#628
0#
#629
1#
b100111001 &
#630
0#
#631
1#
b100111010 &
#632
0#
#633
1#
b100111011 &
#634
0#
#635
1#
b100111100 &
#636
0#
#637
1#
b100111101 &
#638
0#
#639
1#
b100111110 &
#640
0#
#641
1#
b100111111 &
#642
0#
#643
1#
b101000000 &
#644
0#
#645
1#
b101000001 &
#646
0#
#647
1#
b101000010 &
#648
0#
#649
1#
b101000011 &
#650
0#
#651
1#
b101000100 &
#652
0#
#653
1#
b101000101 &
#654
0#
#655
1#
b101000110 &
#656
0#
#657
1#
b101000111 &
#658
0#
#659
1#
b101001000 &
#660
0#
#661
1#
b101001001 &
#662
0#
#663
1#
b101001010 &
#664
0#
#665
1#
b101001011 &
#666
0#
#667
1#
b101001100 &
#668
0#
#669
1#
b101001101 &
#670
0#
#671
1#
b101001110 &
#672
0#
#673
1#
b101001111 &
#674
0#
#675
1#
b101010000 &
#676
0#
#677
1#
b101010001 &
#678
0#
#679
1#
b101010010 &
#680
0#
#681
1#
b101010011 &
#682
0#
#683
1#
b101010100 &
#684
0#
#685
1#
b101010101 &
#686
0#
#687
1#
b101010110 &
#688
0#
#689
1#
b101010111 &
#690
0#
#691
1#
b101011000 &
#692
0#
#693
1#
b101011001 &
#694
0#
#695
1#
b101011010 &
#696
0#
#697
1#
b101011011 &
#698
0#
#699
1#
b101011100 &
#700
0#
#701
1#
b101011101 &
#702
0#
#703
1#
b101011110 &
#704
0#
#705
1#
b101011111 &
#706
0#
#707
1#
b101100000 &
#708
0#
#709
1#
b101100001 &
#710
0#
#711
1#
b101100010 &
#712
0#
#713
1#
b101100011 &
#714
0#
#715
1#
b101100100 &
#716
0#
#717
1#
b101100101 &
#718
0#
#719
1#
b101100110 &
#720
0#
#721
1#
b101100111 &
#722
0#
#723
1#
b101101000 &
#724
0#
#725
1#
b101101001 &
#726
0#
#727
1#
b101101010 &
#728
0#
#729
1#
b101101011 &
#730
0#
#731
1#
b101101100 &
#732
0#
#733
1#
b101101101 &
#734
0#
#735
1#
b101101110 &
#736
0#
#737
1#
b101101111 &
#738
0#
#739
1#
b101110000 &
#740
0#
#741
1#
b101110001 &
#742
0#
#743
1#
b101110010 &
#744
0#
#745
1#
b101110011 &
#746
0#
#747
1#
b101110100 &
#748
0#
#749
1#
b101110101 &
#750
0#
#751
1#
b101110110 &
#752
0#
#753
1#
b101110111 &
#754
0#
#755
1#
b101111000 &
#756
0#
#757
1#
b101111001 &
#758
0#
#759
1#
b101111010 &
#760
0#
#761
1#
b101111011 &
#762
0#
#763
1#
b101111100 &
#764
0#
#765
1#
b101111101 &
#766
0#
#767
1#
b101111110 &
#768
0#
#769
1#
b101111111 &
#770
0#
#771
1#
b110000000 &
#772
0#
#773
1#
b110000001 &
#774
0#
#775
1#
b110000010 &
#776
0#
#777
1#
b110000011 &
#778
0#
#779
1#
b110000100 &
#780
0#
#781
1#
b110000101 &
#782
0#
#783
1#
b110000110 &
#784
0#
#785
1#
b110000111 &
#786
0#
#787
1#
b110001000 &
#788
0#
#789
1#
b110001001 &
#790
0#
#791
1#
b110001010 &
#792
0#
#793
1#
b110001011 &
#794
0#
#795
1#
b110001100 &
#796
0#
#797
1#
b110001101 &
#798
0#
#799
1#
b110001110 &
#800
0#
#801
1#
b110001111 &
#802
0#
#803
1#
b110010000 &
#804
0#
#805
1#
b110010001 &
#806
0#
#807
1#
b110010010 &
#808
0#
#809
1#
b110010011 &
#810
0#
#811
1#
b110010100 &
#812
0#
#813
1#
b110010101 &
#814
0#
#815
1#
b110010110 &
#816
0#
#817
1#
b110010111 &
#818
0#
#819
1#
b110011000 &
#820
0#
#821
1#
b110011001 &
#822
0#
#823
1#
b110011010 &
#824
0#
#825
1#
b110011011 &
#826
0#
#827
1#
b110011100 &
#828
0#
#829
1#
b110011101 &
#830
0#
#831
1#
b110011110 &
#832
0#
#833
1#
b110011111 &
#834
0#
#835
1#
b110100000 &
#836
0#
#837
1#
b110100001 &
#838
0#
#839
1#
b110100010 &
#840
0#
#841
1#
b110100011 &
#842
0#
#843
1#
b110100100 &
#844
0#
#845
1#
b110100101 &
#846
0#
#847
1#
b110100110 &
#848
0#
#849
1#
b110100111 &
#850
0#
#851
1#
b110101000 &
#852
0#
#853
1#
b110101001 &
#854
0#
#855
1#
b110101010 &
#856
0#
#857
1#
b110101011 &
#858
0#
#859
1#
b110101100 &
#860
0#
#861
1#
b110101101 &
#862
0#
#863
1#
b110101110 &
#864
0#
#865
1#
b110101111 &
#866
0#
#867
1#
b110110000 &
#868
0#
#869
1#
b110110001 &
#870
0#
#871
1#
1%
b000000000 &
#872
0#
#873
1#
0%
b000000001 &
#874
0#
#875
1#
b000000010 &
#876
0#
#877
1#
b000000011 &
#878
0#
#879
1#
b000000100 &
#880
0#
#881
1#
b000000101 &
#882
0#
#883
1#
b000000110 &
#884
0#
#885
1#
b000000111 &
#886
0#
#887
1#
b000001000 &
#888
0#
#889
1#
b000001001 &
#890
0#
#891
1#
b000001010 &
#892
0#
#893
1#
b000001011 &
#894
0#
#895
1#
b000001100 &
#896
0#
#897
1#
b000001101 &
#898
0#
#899
1#
b000001110 &
#900
0#
#901
1#
b000001111 &
#902
0#
#903
1#
b000010000 &
#904
0#
#905
1#
b000010001 &
#906
0#
#907
1#
b000010010 &
#908
0#
#909
1#
b000010011 &
#910
0#
#911
1#
b000010100 &
#912
0#
#913
1#
b000010101 &
#914
0#
#915
1#
b000010110 &
#916
0#
#917
1#
b000010111 &
#918
0#
#919
1#
b000011000 &
#920
0#
#921
1#
b000011001 &
#922
0#
#923
1#
b000011010 &
#924
0#
#925
1#
b000011011 &
#926
0#
#927
1#
b000011100 &
#928
0#
#929
1#
b000011101 &
#930
0#
#931
1#
b000011110 &
#932
0#
#933
1#
b000011111 &
#934
0#
#935
1#
b000100000 &
#936
0#
#937
1#
b000100001 &
#938
0#
#939
1#
b000100010 &
#940
0#
#941
1#
b000100011 &
#942
0#
#943
1#
b000100100 &
#944
0#
#945
1#
b000100101 &
#946
0#
#947
1#
b000100110 &
#948
0#
#949
1#
b000100111 &
#950
0#
#951
1#
b000101000 &
#952
0#
#953
1#
b000101001 &
#954
0#
#955
1#
b000101010 &
#956
0#
#957
1#
b000101011 &
#958
0#
#959
1#
b000101100 &
#960
0#
#961
1#
b000101101 &
#962
0#
#963
1#
b000101110 &
#964
0#
#965
1#
b000101111 &
#966
0#
#967
1#
b000110000 &
#968
0#
#969
1#
b000110001 &
#970
0#
#971
1#
b000110010 &
#972
0#
#973
1#
b000110011 &
#974
0#
#975
1#
b000110100 &
#976
0#
#977
1#
b000110101 &
#978
0#
#979
1#
b000110110 &
#980
0#
#981
1#
b000110111 &
#982
0#
#983
1#
b000111000 &
#984
0#
#985
1#
b000111001 &
#986
0#
#987
1#
b000111010 &
#988
0#
#989
1#
b000111011 &
#990
0#
#991
1#
b000111100 &
#992
0#
#993
1#
b000111101 &
#994
0#
#995
1#
b000111110 &
#996
0#
#997
1#
b000111111 &
#998
0#
#999
1#
b001000000 &
#1000
0#
#1001
1#
b001000001 &
#1002
0#
#1003
1#
b001000010 &
#1004
0#
#1005
1#
b001000011 &
#1006
0#
#1007
1#
b001000100 &
#1008
0#
#1009
1#
b001000101 &
#1010
0#
#1011
1#
b001000110 &
#1012
0#
#1013
1#
b001000111 &
#1014
0#
#1015
1#
b001001000 &
#1016
0#
#1017
1#
b001001001 &
#1018
0#
#1019
1#
b001001010 &
#1020
0#
#1021
1#
b001001011 &
#1022
0#
#1023
1#
b001001100 &
#1024
0#
#1025
1#
b001001101 &
#1026
0#
#1027
1#
b001001110 &
#1028
0#
#1029
1#
b001001111 &
#1030
0#
#1031
1#
b001010000 &
#1032
0#
#1033
1#
b001010001 &
#1034
0#
#1035
1#
b001010010 &
#1036
0#
#1037
1#
b001010011 &
#1038
0#
#1039
1#
b001010100 &
#1040
0#
#1041
1#
b001010101 &
#1042
0#
#1043
1#
b001010110 &
#1044
0#
#1045
1#
b001010111 &
#1046
0#
#1047
1#
b001011000 &
#1048
0#
#1049
1#
b001011001 &
#1050
0#
#1051
1#
b001011010 &
#1052
0#
#1053
1#
b001011011 &
#1054
0#
#1055
1#
b001011100 &
#1056
0#
#1057
1#
b001011101 &
#1058
0#
#1059
1#
b001011110 &
#1060
0#
#1061
1#
b001011111 &
#1062
0#
#1063
1#
b001100000 &
#1064
0#
#1065
1#
b001100001 &
#1066
0#
#1067
1#
b001100010 &
#1068
0#
#1069
1#
b001100011 &
#1070
0#
#1071
1#
b001100100 &
#1072
0#
#1073
1#
b001100101 &
#1074
0#
#1075
1#
b001100110 &
#1076
0#
#1077
1#
b001100111 &
#1078
0#
#1079
1#
b001101000 &
#1080
0#
#1081
1#
b001101001 &
#1082
0#
#1083
1#
b001101010 &
#1084
0#
#1085
1#
b001101011 &
#1086
0#
#1087
1#
b001101100 &
#1088
0#
#1089
1#
b001101101 &
#1090
0#
#1091
1#
b001101110 &
#1092
0#
#1093
1#
b001101111 &
#1094
0#
#1095
1#
b001110000 &
#1096
0#
#1097
1#
b001110001 &
#1098
0#
#1099
1#
b001110010 &
#1100
0#
#1101
1#
b001110011 &
#1102
0#
#1103
1#
b001110100 &
#1104
0#
#1105
1#
b001110101 &
#1106
0#
#1107
1#
b001110110 &
#1108
0#
#1109
1#
b001110111 &
#1110
0#
#1111
1#
b001111000 &
#1112
0#
#1113
1#
b001111001 &
#1114
0#
#1115
1#
b001111010 &
#1116
0#
#1117
1#
b001111011 &
#1118
0#
#1119
1#
b001111100 &
#1120
0#
#1121
1#
b001111101 &
#1122
0#
#1123
1#
b001111110 &
#1124
0#
#1125
1#
b001111111 &
#1126
0#
#1127
1#
b010000000 &
#1128
0#
#1129
1#
b010000001 &
#1130
0#
#1131
1#
b010000010 &
#1132
0#
#1133
1#
b010000011 &
#1134
0#
#1135
1#
b010000100 &
#1136
0#
#1137
1#
b010000101 &
#1138
0#
#1139
1#
b010000110 &
#1140
0#
#1141
1#
b010000111 &
#1142
0#
#1143
1#
b010001000 &
#1144
0#
#1145
1#
b010001001 &
#1146
0#
#1147
1#
b010001010 &
#1148
0#
#1149
1#
b010001011 &
#1150
0#
#1151
1#
b010001100 &
#1152
0#
#1153
1#
b010001101 &
#1154
0#
#1155
1#
b010001110 &
#1156
0#
#1157
1#
b010001111 &
#1158
0#
#1159
1#
b010010000 &
#1160
0#
#1161
1#
b010010001 &
#1162
0#
#1163
1#
b010010010 &
#1164
0#
#1165
1#
b010010011 &
#1166
0#
#1167
1#
b010010100 &
#1168
0#
#1169
1#
b010010101 &
#1170
0#
#1171
1#
b010010110 &
#1172
0#
#1173
1#
b010010111 &
#1174
0#
#1175
1#
b010011000 &
#1176
0#
#1177
1#
b010011001 &
#1178
0#
#1179
1#
b010011010 &
#1180
0#
#1181
1#
b010011011 &
#1182
0#
#1183
1#
b010011100 &
#1184
0#
#1185
1#
b010011101 &
#1186
0#
#1187
1#
b010011110 &
#1188
0#
#1189
1#
b010011111 &
#1190
0#
#1191
1#
b010100000 &
#1192
0#
#1193
1#
b010100001 &
#1194
0#
#1195
1#
b010100010 &
#1196
0#
#1197
1#
b010100011 &
#1198
0#
#1199
1#
b010100100 &
#1200
0#
#1201
1#
b010100101 &
#1202
0#
#1203
1#
b010100110 &
#1204
0#
#1205
1#
b010100111 &
