fifo_uart/rtl/sync_fifo.sv
module sync_fifo #(
    parameter int DATA_W = 8,
    parameter int DEPTH  = 16,
    parameter int ADDR_W = $clog2(DEPTH)
) (
    input  logic              clk,
    input  logic              rst_n,
    input  logic              wr_en,
    input  logic [DATA_W-1:0] in_data,
    input  logic              rd_en,
    output logic [DATA_W-1:0] out_data,
    output logic              full,
    output logic              empty
);

    logic [DATA_W-1:0] mem [0:DEPTH-1];
    logic [ADDR_W:0] wr_ptr;
    logic [ADDR_W:0] rd_ptr;

    always_ff @(posedge clk or negedge rst_n) begin
        if (!rst_n) begin
            wr_ptr <= '0;
        end else if (wr_en && !full) begin
            mem[wr_ptr[ADDR_W-1:0]] <= in_data;
            wr_ptr <= wr_ptr + 1'b1;
        end
    end

    always_ff @(posedge clk or negedge rst_n) begin
        if (!rst_n) begin
            rd_ptr   <= '0;
            out_data <= '0;
        end else if (rd_en && !empty) begin
            out_data <= mem[rd_ptr[ADDR_W-1:0]];
            rd_ptr   <= rd_ptr + 1'b1;
        end
    end

    assign empty = (wr_ptr == rd_ptr);
    assign full  = (wr_ptr[ADDR_W] != rd_ptr[ADDR_W]) &&
                   (wr_ptr[ADDR_W-1:0] == rd_ptr[ADDR_W-1:0]);

endmodule

tb/tb_sync_fifo.sv
module tb_sync_fifo;

    parameter int DATA_W = 8;
    parameter int DEPTH  = 16;
    parameter int ADDR_W = $clog2(DEPTH);

    logic clk;
    logic rst_n;
    logic wr_en;
    logic rd_en;
    logic [DATA_W-1:0] in_data;
    logic [DATA_W-1:0] out_data;
    logic full;
    logic empty;

    sync_fifo #(
        .DATA_W(DATA_W),
        .DEPTH(DEPTH),
        .ADDR_W(ADDR_W)
    ) dut (
        .clk(clk),
        .rst_n(rst_n),
        .wr_en(wr_en),
        .in_data(in_data),
        .rd_en(rd_en),
        .out_data(out_data),
        .full(full),
        .empty(empty)
    );

    logic [DATA_W-1:0] model_q[$];

    initial clk = 0;
    always #5 clk = ~clk;

    task automatic reset_dut();
        rst_n   = 0;
        wr_en   = 0;
        rd_en   = 0;
        in_data = '0;
        model_q.delete();
        repeat (3) @(posedge clk);
        rst_n = 1;
        repeat (1) @(posedge clk);
    endtask

    task automatic push(input logic [DATA_W-1:0] data);
        @(posedge clk);
        if (!full) begin
            wr_en   = 1;
            rd_en   = 0;
            in_data = data;
            model_q.push_back(data);
        end else begin
            wr_en = 0;
        end
        @(posedge clk);
        wr_en = 0;
    endtask

    task automatic pop();
        logic [DATA_W-1:0] exp;
        bit do_compare;
        @(posedge clk);
        do_compare = 0;
        if (!empty) begin
            wr_en = 0;
            rd_en = 1;
            if (model_q.size() > 0) begin
                exp = model_q.pop_front();
                do_compare = 1;
            end
        end else begin
            rd_en = 0;
        end
        @(posedge clk);
        if (do_compare && out_data !== exp)
            $error("DATA MISMATCH time=%0t exp=%0h got=%0h", $time, exp, out_data);
        rd_en = 0;
    endtask

    task automatic check_flags();
        if (empty !== (model_q.size() == 0))
            $error("EMPTY mismatch time=%0t exp=%0b got=%0b", $time, (model_q.size() == 0), empty);

        if (full !== (model_q.size() == DEPTH))
            $error("FULL mismatch time=%0t exp=%0b got=%0b", $time, (model_q.size() == DEPTH), full);
    endtask

    initial begin
        reset_dut();

        push(8'h11);
        push(8'h22);
        push(8'h33);
        check_flags();

        pop();
        pop();
        check_flags();

        repeat (DEPTH) push (logic'($urandom_range(0, 255)));
        check_flags();

        repeat (DEPTH) pop();
        check_flags();

        $finish;
    end

endmodule

tb_sync_fifo.vcd
$version Generated by VerilatedVcd $end
$timescale 1ps $end
 $scope module TOP $end
  $scope module tb_sync_fifo $end
   $var wire 32 = DATA_W [31:0] $end
   $var wire 32 > DEPTH [31:0] $end
   $var wire 32 ? ADDR_W [31:0] $end
   $var wire 1 8 clk $end
   $var wire 1 9 rst_n $end
   $var wire 1 : wr_en $end
   $var wire 1 ; rd_en $end
   $var wire 8 < in_data [7:0] $end
   $var wire 8 # out_data [7:0] $end
   $var wire 1 $ full $end
   $var wire 1 % empty $end
   $scope module dut $end
    $var wire 32 = DATA_W [31:0] $end
    $var wire 32 > DEPTH [31:0] $end
    $var wire 32 ? ADDR_W [31:0] $end
    $var wire 1 8 clk $end
    $var wire 1 9 rst_n $end
    $var wire 1 : wr_en $end
    $var wire 8 < in_data [7:0] $end
    $var wire 1 ; rd_en $end
    $var wire 8 # out_data [7:0] $end
    $var wire 1 $ full $end
    $var wire 1 % empty $end
    $var wire 8 & mem[0] [7:0] $end
    $var wire 8 ' mem[1] [7:0] $end
    $var wire 8 ( mem[2] [7:0] $end
    $var wire 8 ) mem[3] [7:0] $end
    $var wire 8 * mem[4] [7:0] $end
    $var wire 8 + mem[5] [7:0] $end
    $var wire 8 , mem[6] [7:0] $end
    $var wire 8 - mem[7] [7:0] $end
    $var wire 8 . mem[8] [7:0] $end
    $var wire 8 / mem[9] [7:0] $end
    $var wire 8 0 mem[10] [7:0] $end
    $var wire 8 1 mem[11] [7:0] $end
    $var wire 8 2 mem[12] [7:0] $end
    $var wire 8 3 mem[13] [7:0] $end
    $var wire 8 4 mem[14] [7:0] $end
    $var wire 8 5 mem[15] [7:0] $end
    $var wire 5 6 wr_ptr [4:0] $end
    $var wire 5 7 rd_ptr [4:0] $end
    $scope module u_assert_sync_fifo $end
     $var wire 32 ? ADDR_W [31:0] $end
     $var wire 1 8 clk $end
     $var wire 1 9 rst_n $end
     $var wire 1 : wr_en $end
     $var wire 1 ; rd_en $end
     $var wire 1 $ full $end
     $var wire 1 % empty $end
     $var wire 5 6 wr_ptr [4:0] $end
     $var wire 5 7 rd_ptr [4:0] $end
    $upscope $end
   $upscope $end
  $upscope $end
 $upscope $end
$enddefinitions $end


#0
b00000000 #
0$
1%
b00000000 &
b00000000 '
b00000000 (
b00000000 )
b00000000 *
b00000000 +
b00000000 ,
b00000000 -
b00000000 .
b00000000 /
b00000000 0
b00000000 1
b00000000 2
b00000000 3
b00000000 4
b00000000 5
b00000 6
b00000 7
08
09
0:
0;
b00000000 <
b00000000000000000000000000001000 =
b00000000000000000000000000010000 >
b00000000000000000000000000000100 ?
#5
18
#10
08
#15
18
#20
08
#25
18
19
#30
08
#35
18
#40
08
#45
0%
b00010001 &
b00001 6
18
1:
b00010001 <
#50
08
#55
18
0:
#60
08
#65
b00100010 '
b00010 6
18
1:
b00100010 <
#70
08
#75
18
0:
#80
08
#85
b00110011 (
b00011 6
18
1:
b00110011 <
#90
08
#95
18
0:
#100
08
#105
b00010001 #
b00001 7
18
1;
#110
08
#115
18
0;
#120
08
#125
b00100010 #
b00010 7
18
1;
#130
08
#135
18
0;
#140
08
#145
b11000100 )
b00100 6
18
1:
b11000100 <
#150
08
#155
18
0:
#160
08
#165
b10011100 *
b00101 6
18
1:
b10011100 <
#170
08
#175
18
0:
#180
08
#185
b00000010 +
b00110 6
18
1:
b00000010 <
#190
08
#195
18
0:
#200
08
#205
b11100100 ,
b00111 6
18
1:
b11100100 <
#210
08
#215
18
0:
#220
08
#225
b01111000 -
b01000 6
18
1:
b01111000 <
#230
08
#235
18
0:
#240
08
#245
b10111100 .
b01001 6
18
1:
b10111100 <
#250
08
#255
18
0:
#260
08
#265
b10110110 /
b01010 6
18
1:
b10110110 <
#270
08
#275
18
0:
#280
08
#285
b11100100 0
b01011 6
18
1:
b11100100 <
#290
08
#295
18
0:
#300
08
#305
b10110111 1
b01100 6
18
1:
b10110111 <
#310
08
#315
18
0:
#320
08
#325
b01010011 2
b01101 6
18
1:
b01010011 <
#330
08
#335
18
0:
#340
08
#345
b00100001 3
b01110 6
18
1:
b00100001 <
#350
08
#355
18
0:
#360
08
#365
b11100001 4
b01111 6
18
1:
b11100001 <
#370
08
#375
18
0:
#380
08
#385
b11000101 5
b10000 6
18
1:
b11000101 <
#390
08
#395
18
0:
#400
08
#405
b10000010 &
b10001 6
18
1:
b10000010 <
#410
08
#415
18
0:
#420
08
#425
1$
b01100010 '
b10010 6
18
1:
b01100010 <
#430
08
#435
18
0:
#440
08
#445
18
#450
08
#455
18
#460
08
#465
b00110011 #
0$
b00011 7
18
1;
#470
08
#475
18
0;
#480
08
#485
b11000100 #
b00100 7
18
1;
#490
08
#495
18
0;
#500
08
#505
b10011100 #
b00101 7
18
1;
#510
08
#515
18
0;
#520
08
#525
b00000010 #
b00110 7
18
1;
#530
08
#535
18
0;
#540
08
#545
b11100100 #
b00111 7
18
1;
#550
08
#555
18
0;
#560
08
#565
b01111000 #
b01000 7
18
1;
#570
08
#575
18
0;
#580
08
#585
b10111100 #
b01001 7
18
1;
#590
08
#595
18
0;
#600
08
#605
b10110110 #
b01010 7
18
1;
#610
08
#615
18
0;
#620
08
#625
b11100100 #
b01011 7
18
1;
#630
08
#635
18
0;
#640
08
#645
b10110111 #
b01100 7
18
1;
#650
08
#655
18
0;
#660
08
#665
b01010011 #
b01101 7
18
1;
#670
08
#675
18
0;
#680
08
#685
b00100001 #
b01110 7
18
1;
#690
08
#695
18
0;
#700
08
#705
b11100001 #
b01111 7
18
1;
#710
08
#715
18
0;
#720
08
#725
b11000101 #
b10000 7
18
1;
#730
08
#735
18
0;
#740
08
#745
b10000010 #
b10001 7
18
1;
#750
08
#755
18
0;
#760
08
#765
b01100010 #
1%
b10010 7
18
1;
#770
08
#775
18
0;
