pcie-sg-dma-engine/pcie-sg-dma-engine/rtl/descriptor_engine/desc_ring_mgr.sv
//==============================================================================
// desc_ring_mgr.sv
// Descriptor Ring Manager: maintains insert/extract pointers for the
// scatter-gather descriptor ring. Ring lives in host memory; hardware
// mirrors insert/extract pointers locally and exposes them via BAR registers.
//
// Ring depth is fixed at compile time. Pointer width includes one extra MSB
// beyond the index width so that full/empty can be distinguished unambiguously
// (classic FIFO pointer trick, applied here to a descriptor ring instead of
// a data FIFO).
//==============================================================================
module desc_ring_mgr #(
    parameter int RING_DEPTH  = 128,                       // must be power of 2
    parameter int PTR_WIDTH   = $clog2(RING_DEPTH) + 1      // extra bit for wrap disambiguation
)(
    input  logic                  clk,
    input  logic                  rst_n,

    // Software-facing (BAR-mapped) interface
    input  logic [PTR_WIDTH-1:0]  sw_insert_ptr_wr,   // value software writes to advance insert ptr
    input  logic                  sw_insert_ptr_wr_en,
    output logic [PTR_WIDTH-1:0]  hw_extract_ptr_rd,  // value software reads to know hw progress

    // Internal engine interface
    output logic [PTR_WIDTH-1:0]  insert_ptr,
    output logic [PTR_WIDTH-1:0]  extract_ptr,
    input  logic                  extract_ptr_update,  // pulse: advance extract_ptr by 1
    input  logic                  extract_valid_req,   // engine wants to know if a descriptor is available

    output logic                  ring_empty,
    output logic                  ring_full,
    output logic                  extract_valid,       // 1 = a valid descriptor is available to fetch

    // Debug / assertion taps (used by tb/assertions/sva_descriptor_invariants.sv via bind)
    output logic                  insert_ptr_update_dbg,
    output logic                  extract_ptr_update_dbg
);

    logic [PTR_WIDTH-1:0] insert_ptr_r, extract_ptr_r;

    // ---------------------------------------------------------------
    // Insert pointer: driven by software via BAR write. In a real
    // implementation this register is memory-mapped; sw_insert_ptr_wr_en
    // is generated by the AXI4-Lite/MM register block, not shown here.
    // ---------------------------------------------------------------
    always_ff @(posedge clk or negedge rst_n) begin
        if (!rst_n) begin
            insert_ptr_r <= '0;
        end else if (sw_insert_ptr_wr_en) begin
            insert_ptr_r <= sw_insert_ptr_wr;
        end
    end

    // ---------------------------------------------------------------
    // Extract pointer: driven by hardware as descriptors are consumed.
    // Only advances one at a time, gated by extract_ptr_update pulse
    // from desc_fetch.sv after WRITEBACK completes for that descriptor.
    // ---------------------------------------------------------------
    always_ff @(posedge clk or negedge rst_n) begin
        if (!rst_n) begin
            extract_ptr_r <= '0;
        end else if (extract_ptr_update) begin
            extract_ptr_r <= extract_ptr_r + 1'b1;
        end
    end

    assign insert_ptr  = insert_ptr_r;
    assign extract_ptr = extract_ptr_r;
    assign hw_extract_ptr_rd = extract_ptr_r;

    // ---------------------------------------------------------------
    // Empty/full computed using the extra-bit trick:
    // empty  when insert_ptr == extract_ptr (all bits equal, including MSB)
    // full   when index bits equal but MSB differs (wrapped exactly RING_DEPTH ahead)
    // ---------------------------------------------------------------
    assign ring_empty = (insert_ptr_r == extract_ptr_r);
    assign ring_full  = (insert_ptr_r[PTR_WIDTH-2:0] == extract_ptr_r[PTR_WIDTH-2:0]) &&
                         (insert_ptr_r[PTR_WIDTH-1]   != extract_ptr_r[PTR_WIDTH-1]);

    assign extract_valid = extract_valid_req && !ring_empty;

    // Debug taps for assertion binding
    assign insert_ptr_update_dbg  = sw_insert_ptr_wr_en;
    assign extract_ptr_update_dbg = extract_ptr_update;

endmodule

pcie-sg-dma-engine/pcie-sg-dma-engine/tb/directed/tb_ring_wraparound.sv
//==============================================================================
// tb_ring_wraparound.sv
// Directed test: fill the ring exactly to RING_DEPTH-1, drain it while
// filling more, and force the insert pointer past the ADDR_WIDTH boundary
// to verify wraparound math (insert_ptr - extract_ptr) never miscomputes.
//==============================================================================
`timescale 1ns/1ps

module tb_ring_wraparound;

    localparam RING_DEPTH = 128;
    localparam PTR_WIDTH  = $clog2(RING_DEPTH) + 1;

    logic clk = 0, rst_n = 0;
    logic [PTR_WIDTH-1:0] sw_insert_ptr_wr;
    logic sw_insert_ptr_wr_en;
    logic [PTR_WIDTH-1:0] hw_extract_ptr_rd;
    logic [PTR_WIDTH-1:0] insert_ptr, extract_ptr;
    logic extract_ptr_update, extract_valid_req, extract_valid;
    logic ring_empty, ring_full;

    int pass_count = 0;
    int fail_count = 0;

    always #5 clk = ~clk;

    desc_ring_mgr #(.RING_DEPTH(RING_DEPTH)) dut (
        .clk, .rst_n,
        .sw_insert_ptr_wr, .sw_insert_ptr_wr_en, .hw_extract_ptr_rd,
        .insert_ptr, .extract_ptr,
        .extract_ptr_update, .extract_valid_req,
        .ring_empty, .ring_full, .extract_valid,
        .insert_ptr_update_dbg(), .extract_ptr_update_dbg()
    );

    // Waveform dumping for Verilator
    initial begin
        $dumpfile("tb_ring_wraparound.vcd");
        $dumpvars(0, tb_ring_wraparound);
    end

    task automatic push_n_descriptors(int n);
        for (int i = 0; i < n; i++) begin
            @(posedge clk);
            sw_insert_ptr_wr    = insert_ptr + 1;
            sw_insert_ptr_wr_en = 1;
            @(posedge clk);
            sw_insert_ptr_wr_en = 0;
        end
    endtask

    task automatic drain_n_descriptors(int n);
        for (int i = 0; i < n; i++) begin
            @(posedge clk);
            extract_ptr_update = 1;
            @(posedge clk);
            extract_ptr_update = 0;
        end
    endtask

    task automatic check(input string label, input logic condition);
        if (!condition) begin
            $display("FAIL: %s (time=%0t)", label, $time);
            fail_count++;
        end else begin
            $display("PASS: %s (time=%0t)", label, $time);
            pass_count++;
        end
    endtask

    // Watchdog timer
    initial begin
        #100_000;
        $display("TIMEOUT: test did not complete within 100us");
        $finish;
    end

    initial begin
        rst_n = 0;
        sw_insert_ptr_wr_en = 0;
        extract_ptr_update  = 0;
        extract_valid_req   = 1;
        repeat (5) @(posedge clk);
        rst_n = 1;
        @(posedge clk);

        // ==== Test 1: Initially empty ====
        check("ring starts empty", ring_empty);
        check("ring starts not full", !ring_full);
        check("extract_valid is low when empty", !extract_valid || ring_empty == 0);

        // ==== Test 2: Fill to DEPTH-1 ====
        push_n_descriptors(RING_DEPTH - 1);
        @(posedge clk);
        check("ring not full at DEPTH-1", !ring_full);
        check("ring not empty at DEPTH-1", !ring_empty);

        // ==== Test 3: Fill to DEPTH (full) ====
        push_n_descriptors(1);
        @(posedge clk);
        check("ring full at DEPTH", ring_full);
        check("ring not empty when full", !ring_empty);

        // ==== Test 4: Drain half, push half more (wraparound) ====
        drain_n_descriptors(RING_DEPTH / 2);
        @(posedge clk);
        check("ring not full after draining half", !ring_full);

        push_n_descriptors(RING_DEPTH / 2);
        @(posedge clk);
        check("ring full again after wraparound push", ring_full);
        check("ring not empty after wraparound", !ring_empty);

        // ==== Test 5: Drain all (back to empty) ====
        drain_n_descriptors(RING_DEPTH);
        @(posedge clk);
        check("ring empty after full drain", ring_empty);
        check("ring not full after full drain", !ring_full);

        // ==== Test 6: Push/drain interleaved past multiple wraps ====
        for (int round = 0; round < 3; round++) begin
            push_n_descriptors(RING_DEPTH);
            check($sformatf("round %0d: ring full", round), ring_full);
            drain_n_descriptors(RING_DEPTH);
            @(posedge clk);
            check($sformatf("round %0d: ring empty", round), ring_empty);
        end

        // ==== Summary ====
        $display("\n========================================");
        $display("tb_ring_wraparound: %0d PASS, %0d FAIL", pass_count, fail_count);
        if (fail_count == 0)
            $display("RESULT: ALL TESTS PASSED");
        else
            $display("RESULT: %0d TESTS FAILED", fail_count);
        $display("========================================\n");
        $finish;
    end

endmodule

pcie-sg-dma-engine/pcie-sg-dma-engine/sim_results/waveforms/tb_ring_wraparound.vcd
$version Generated by VerilatedVcd $end
$timescale 1ps $end
 $scope module TOP $end
  $scope module tb_ring_wraparound $end
   $var wire 32 1 RING_DEPTH [31:0] $end
   $var wire 32 2 PTR_WIDTH [31:0] $end
   $var wire 1 / clk $end
   $var wire 1 # rst_n $end
   $var wire 8 $ sw_insert_ptr_wr [7:0] $end
   $var wire 1 % sw_insert_ptr_wr_en $end
   $var wire 8 + hw_extract_ptr_rd [7:0] $end
   $var wire 8 , insert_ptr [7:0] $end
   $var wire 8 + extract_ptr [7:0] $end
   $var wire 1 & extract_ptr_update $end
   $var wire 1 ' extract_valid_req $end
   $var wire 1 0 extract_valid $end
   $var wire 1 - ring_empty $end
   $var wire 1 . ring_full $end
   $var wire 32 ( pass_count [31:0] $end
   $var wire 32 ) fail_count [31:0] $end
   $scope module dut $end
    $var wire 32 3 RING_DEPTH [31:0] $end
    $var wire 32 4 PTR_WIDTH [31:0] $end
    $var wire 1 / clk $end
    $var wire 1 # rst_n $end
    $var wire 8 $ sw_insert_ptr_wr [7:0] $end
    $var wire 1 % sw_insert_ptr_wr_en $end
    $var wire 8 + hw_extract_ptr_rd [7:0] $end
    $var wire 8 , insert_ptr [7:0] $end
    $var wire 8 + extract_ptr [7:0] $end
    $var wire 1 & extract_ptr_update $end
    $var wire 1 ' extract_valid_req $end
    $var wire 1 - ring_empty $end
    $var wire 1 . ring_full $end
    $var wire 1 0 extract_valid $end
    $var wire 1 % insert_ptr_update_dbg $end
    $var wire 1 & extract_ptr_update_dbg $end
    $var wire 8 , insert_ptr_r [7:0] $end
    $var wire 8 + extract_ptr_r [7:0] $end
   $upscope $end
   $scope module unnamedblk3 $end
    $var wire 32 * round [31:0] $end
   $upscope $end
  $upscope $end
 $upscope $end
$enddefinitions $end


#0
0#
b00000000 $
0%
0&
1'
b00000000000000000000000000000000 (
b00000000000000000000000000000000 )
b00000000000000000000000000000000 *
b00000000 +
b00000000 ,
1-
0.
0/
00
b00000000000000000000000010000000 1
b00000000000000000000000000001000 2
b00000000000000000000000010000000 3
b00000000000000000000000000001000 4
#5000
1/
#10000
0/
#15000
1/
#20000
0/
#25000
1/
#30000
0/
#35000
1/
#40000
0/
#45000
1#
1/
#50000
0/
#55000
b00000000000000000000000000000011 (
1/
#60000
0/
#65000
b00000001 $
1%
b00000001 ,
0-
1/
10
#70000
0/
#75000
0%
1/
#80000
0/
#85000
b00000010 $
1%
b00000010 ,
1/
#90000
0/
#95000
0%
1/
#100000
0/
#105000
b00000011 $
1%
b00000011 ,
1/
#110000
0/
#115000
0%
1/
#120000
0/
#125000
b00000100 $
1%
b00000100 ,
1/
#130000
0/
#135000
0%
1/
#140000
0/
#145000
b00000101 $
1%
b00000101 ,
1/
#150000
0/
#155000
0%
1/
#160000
0/
#165000
b00000110 $
1%
b00000110 ,
1/
#170000
0/
#175000
0%
1/
#180000
0/
#185000
b00000111 $
1%
b00000111 ,
1/
#190000
0/
#195000
0%
1/
#200000
0/
#205000
b00001000 $
1%
b00001000 ,
1/
#210000
0/
#215000
0%
1/
#220000
0/
#225000
b00001001 $
1%
b00001001 ,
1/
#230000
0/
#235000
0%
1/
#240000
0/
#245000
b00001010 $
1%
b00001010 ,
1/
#250000
0/
#255000
0%
1/
#260000
0/
#265000
b00001011 $
1%
b00001011 ,
1/
#270000
0/
#275000
0%
1/
#280000
0/
#285000
b00001100 $
1%
b00001100 ,
1/
#290000
0/
#295000
0%
1/
#300000
0/
#305000
b00001101 $
1%
b00001101 ,
1/
#310000
0/
#315000
0%
1/
#320000
0/
#325000
b00001110 $
1%
b00001110 ,
1/
#330000
0/
#335000
0%
1/
#340000
0/
#345000
b00001111 $
1%
b00001111 ,
1/
#350000
0/
#355000
0%
1/
#360000
0/
#365000
b00010000 $
1%
b00010000 ,
1/
#370000
0/
#375000
0%
1/
#380000
0/
#385000
b00010001 $
1%
b00010001 ,
1/
#390000
0/
#395000
0%
1/
#400000
0/
#405000
b00010010 $
1%
b00010010 ,
1/
#410000
0/
#415000
0%
1/
#420000
0/
#425000
b00010011 $
1%
b00010011 ,
1/
#430000
0/
#435000
0%
1/
#440000
0/
#445000
b00010100 $
1%
b00010100 ,
1/
#450000
0/
#455000
0%
1/
#460000
0/
#465000
b00010101 $
1%
b00010101 ,
1/
#470000
0/
#475000
0%
1/
#480000
0/
#485000
b00010110 $
1%
b00010110 ,
1/
#490000
0/
#495000
0%
1/
#500000
0/
#505000
b00010111 $
1%
b00010111 ,
1/
#510000
0/
#515000
0%
1/
#520000
0/
#525000
b00011000 $
1%
b00011000 ,
1/
#530000
0/
#535000
0%
1/
#540000
0/
#545000
b00011001 $
1%
b00011001 ,
1/
#550000
0/
#555000
0%
1/
#560000
0/
#565000
b00011010 $
1%
b00011010 ,
1/
#570000
0/
#575000
0%
1/
#580000
0/
#585000
b00011011 $
1%
b00011011 ,
1/
#590000
0/
#595000
0%
1/
#600000
0/
#605000
b00011100 $
1%
b00011100 ,
1/
#610000
0/
#615000
0%
1/
#620000
0/
#625000
b00011101 $
1%
b00011101 ,
1/
#630000
0/
#635000
0%
1/
#640000
0/
#645000
b00011110 $
1%
b00011110 ,
1/
#650000
0/
#655000
0%
1/
#660000
0/
#665000
b00011111 $
1%
b00011111 ,
1/
#670000
0/
#675000
0%
1/
#680000
0/
#685000
b00100000 $
1%
b00100000 ,
1/
#690000
0/
#695000
0%
1/
#700000
0/
#705000
b00100001 $
1%
b00100001 ,
1/
#710000
0/
#715000
0%
1/
#720000
0/
#725000
b00100010 $
1%
b00100010 ,
1/
#730000
0/
#735000
0%
1/
#740000
0/
#745000
b00100011 $
1%
b00100011 ,
1/
#750000
0/
#755000
0%
1/
#760000
0/
#765000
b00100100 $
1%
b00100100 ,
1/
#770000
0/
#775000
0%
1/
#780000
0/
#785000
b00100101 $
1%
b00100101 ,
1/
#790000
0/
#795000
0%
1/
#800000
0/
#805000
b00100110 $
1%
b00100110 ,
1/
#810000
0/
#815000
0%
1/
#820000
0/
#825000
b00100111 $
1%
b00100111 ,
1/
#830000
0/
#835000
0%
1/
#840000
0/
#845000
b00101000 $
1%
b00101000 ,
1/
#850000
0/
#855000
0%
1/
#860000
0/
#865000
b00101001 $
1%
b00101001 ,
1/
#870000
0/
#875000
0%
1/
#880000
0/
#885000
b00101010 $
1%
b00101010 ,
1/
#890000
0/
#895000
0%
1/
#900000
0/
#905000
b00101011 $
1%
b00101011 ,
1/
#910000
0/
#915000
0%
1/
#920000
0/
#925000
b00101100 $
1%
b00101100 ,
1/
#930000
0/
#935000
0%
1/
#940000
0/
#945000
b00101101 $
1%
b00101101 ,
1/
#950000
0/
#955000
0%
1/
#960000
0/
#965000
b00101110 $
1%
b00101110 ,
1/
#970000
0/
#975000
0%
1/
#980000
0/
#985000
b00101111 $
1%
b00101111 ,
1/
#990000
0/
#995000
0%
1/
#1000000
0/
#1005000
b00110000 $
1%
b00110000 ,
1/
#1010000
0/
#1015000
0%
1/
#1020000
0/
#1025000
b00110001 $
1%
b00110001 ,
1/
#1030000
0/
#1035000
0%
1/
#1040000
0/
#1045000
b00110010 $
1%
b00110010 ,
1/
#1050000
0/
#1055000
0%
1/
#1060000
0/
#1065000
b00110011 $
1%
b00110011 ,
1/
#1070000
0/
#1075000
0%
1/
#1080000
0/
#1085000
b00110100 $
1%
b00110100 ,
1/
#1090000
0/
#1095000
0%
1/
#1100000
0/
#1105000
b00110101 $
1%
b00110101 ,
1/
#1110000
0/
#1115000
0%
1/
#1120000
0/
#1125000
b00110110 $
1%
b00110110 ,
1/
#1130000
0/
#1135000
0%
1/
#1140000
0/
#1145000
b00110111 $
1%
b00110111 ,
1/
#1150000
0/
#1155000
0%
1/
#1160000
0/
#1165000
b00111000 $
1%
b00111000 ,
1/
#1170000
0/
#1175000
0%
1/
#1180000
0/
#1185000
b00111001 $
1%
b00111001 ,
1/
#1190000
0/
#1195000
0%
1/
#1200000
0/
#1205000
b00111010 $
1%
b00111010 ,
1/
#1210000
0/
#1215000
0%
1/
#1220000
0/
#1225000
b00111011 $
1%
b00111011 ,
1/
#1230000
0/
#1235000
0%
1/
#1240000
0/
#1245000
b00111100 $
1%
b00111100 ,
1/
#1250000
0/
#1255000
0%
1/
#1260000
0/
#1265000
b00111101 $
1%
b00111101 ,
1/
#1270000
0/
#1275000
0%
1/
#1280000
0/
#1285000
b00111110 $
1%
b00111110 ,
1/
#1290000
0/
#1295000
0%
1/
#1300000
0/
#1305000
b00111111 $
1%
b00111111 ,
1/
#1310000
0/
#1315000
0%
1/
#1320000
0/
#1325000
b01000000 $
1%
b01000000 ,
1/
#1330000
0/
#1335000
0%
1/
#1340000
0/
#1345000
b01000001 $
1%
b01000001 ,
1/
#1350000
0/
#1355000
0%
1/
#1360000
0/
#1365000
b01000010 $
1%
b01000010 ,
1/
#1370000
0/
#1375000
0%
1/
#1380000
0/
#1385000
b01000011 $
1%
b01000011 ,
1/
#1390000
0/
#1395000
0%
1/
#1400000
0/
#1405000
b01000100 $
1%
b01000100 ,
1/
#1410000
0/
#1415000
0%
1/
#1420000
0/
#1425000
b01000101 $
1%
b01000101 ,
1/
#1430000
0/
#1435000
0%
1/
#1440000
0/
#1445000
b01000110 $
1%
b01000110 ,
1/
#1450000
0/
#1455000
0%
1/
#1460000
0/
#1465000
b01000111 $
1%
b01000111 ,
1/
#1470000
0/
#1475000
0%
1/
#1480000
0/
#1485000
b01001000 $
1%
b01001000 ,
1/
#1490000
0/
#1495000
0%
1/
#1500000
0/
#1505000
b01001001 $
1%
b01001001 ,
1/
#1510000
0/
#1515000
0%
1/
#1520000
0/
#1525000
b01001010 $
1%
b01001010 ,
1/
#1530000
0/
#1535000
0%
1/
#1540000
0/
#1545000
b01001011 $
1%
b01001011 ,
1/
#1550000
0/
#1555000
0%
1/
#1560000
0/
#1565000
b01001100 $
1%
b01001100 ,
1/
#1570000
0/
#1575000
0%
1/
#1580000
0/
#1585000
b01001101 $
1%
b01001101 ,
1/
#1590000
0/
#1595000
0%
1/
#1600000
0/
#1605000
b01001110 $
1%
b01001110 ,
1/
#1610000
0/
#1615000
0%
1/
#1620000
0/
#1625000
b01001111 $
1%
b01001111 ,
1/
#1630000
0/
#1635000
0%
1/
#1640000
0/
#1645000
b01010000 $
1%
b01010000 ,
1/
#1650000
0/
#1655000
0%
1/
#1660000
0/
#1665000
b01010001 $
1%
b01010001 ,
1/
#1670000
0/
#1675000
0%
1/
#1680000
0/
#1685000
b01010010 $
1%
b01010010 ,
1/
#1690000
0/
#1695000
0%
1/
#1700000
0/
#1705000
b01010011 $
1%
b01010011 ,
1/
#1710000
0/
#1715000
0%
1/
#1720000
0/
#1725000
b01010100 $
1%
b01010100 ,
1/
#1730000
0/
#1735000
0%
1/
#1740000
0/
#1745000
b01010101 $
1%
b01010101 ,
1/
#1750000
0/
#1755000
0%
1/
#1760000
0/
#1765000
b01010110 $
1%
b01010110 ,
1/
#1770000
0/
#1775000
0%
1/
#1780000
0/
#1785000
b01010111 $
1%
b01010111 ,
1/
#1790000
0/
#1795000
0%
1/
#1800000
0/
#1805000
b01011000 $
1%
b01011000 ,
1/
#1810000
0/
#1815000
0%
1/
#1820000
0/
#1825000
b01011001 $
1%
b01011001 ,
1/
#1830000
0/
#1835000
0%
1/
#1840000
0/
#1845000
b01011010 $
1%
b01011010 ,
1/
#1850000
0/
#1855000
0%
1/
#1860000
0/
#1865000
b01011011 $
1%
b01011011 ,
1/
#1870000
0/
#1875000
0%
1/
#1880000
0/
#1885000
b01011100 $
1%
b01011100 ,
1/
#1890000
0/
#1895000
0%
1/
#1900000
0/
#1905000
b01011101 $
1%
b01011101 ,
1/
#1910000
0/
#1915000
0%
1/
#1920000
0/
#1925000
b01011110 $
1%
b01011110 ,
1/
#1930000
0/
#1935000
0%
1/
#1940000
0/
#1945000
b01011111 $
1%
b01011111 ,
1/
#1950000
0/
#1955000
0%
1/
#1960000
0/
#1965000
b01100000 $
1%
b01100000 ,
1/
#1970000
0/
#1975000
0%
1/
#1980000
0/
#1985000
b01100001 $
1%
b01100001 ,
1/
#1990000
0/
#1995000
0%
1/
#2000000
0/
#2005000
b01100010 $
1%
b01100010 ,
1/
#2010000
0/
#2015000
0%
1/
#2020000
0/
#2025000
b01100011 $
1%
b01100011 ,
1/
#2030000
0/
#2035000
0%
1/
#2040000
0/
#2045000
b01100100 $
1%
b01100100 ,
1/
#2050000
0/
#2055000
0%
1/
#2060000
0/
#2065000
b01100101 $
1%
b01100101 ,
1/
#2070000
0/
#2075000
0%
1/
#2080000
0/
#2085000
b01100110 $
1%
b01100110 ,
1/
#2090000
0/
#2095000
0%
1/
#2100000
0/
#2105000
b01100111 $
1%
b01100111 ,
1/
#2110000
0/
#2115000
0%
1/
#2120000
0/
#2125000
b01101000 $
1%
b01101000 ,
1/
#2130000
0/
#2135000
0%
1/
#2140000
0/
#2145000
b01101001 $
1%
b01101001 ,
1/
#2150000
0/
#2155000
0%
1/
#2160000
0/
#2165000
b01101010 $
1%
b01101010 ,
1/
#2170000
0/
#2175000
0%
1/
#2180000
0/
#2185000
b01101011 $
1%
b01101011 ,
1/
#2190000
0/
#2195000
0%
1/
#2200000
0/
#2205000
b01101100 $
1%
b01101100 ,
1/
#2210000
0/
#2215000
0%
1/
#2220000
0/
#2225000
b01101101 $
1%
b01101101 ,
1/
#2230000
0/
#2235000
0%
1/
#2240000
0/
#2245000
b01101110 $
1%
b01101110 ,
1/
#2250000
0/
#2255000
0%
1/
#2260000
0/
#2265000
b01101111 $
1%
b01101111 ,
1/
#2270000
0/
#2275000
0%
1/
#2280000
0/
#2285000
b01110000 $
1%
b01110000 ,
1/
#2290000
0/
#2295000
0%
1/
#2300000
0/
#2305000
b01110001 $
1%
b01110001 ,
1/
#2310000
0/
#2315000
0%
1/
#2320000
0/
#2325000
b01110010 $
1%
b01110010 ,
1/
#2330000
0/
#2335000
0%
1/
#2340000
0/
#2345000
b01110011 $
1%
b01110011 ,
1/
#2350000
0/
#2355000
0%
1/
#2360000
0/
#2365000
b01110100 $
1%
b01110100 ,
1/
#2370000
0/
#2375000
0%
1/
#2380000
0/
#2385000
b01110101 $
1%
b01110101 ,
1/
#2390000
0/
#2395000
0%
1/
#2400000
0/
#2405000
b01110110 $
1%
b01110110 ,
1/
#2410000
0/
#2415000
0%
1/
#2420000
0/
#2425000
b01110111 $
1%
b01110111 ,
1/
#2430000
0/
#2435000
0%
1/
#2440000
0/
#2445000
b01111000 $
1%
b01111000 ,
1/
#2450000
0/
#2455000
0%
1/
#2460000
0/
#2465000
b01111001 $
1%
b01111001 ,
1/
#2470000
0/
#2475000
0%
1/
#2480000
0/
#2485000
b01111010 $
1%
b01111010 ,
1/
#2490000
0/
#2495000
0%
1/
#2500000
0/
#2505000
b01111011 $
1%
b01111011 ,
1/
#2510000
0/
#2515000
0%
1/
#2520000
0/
#2525000
b01111100 $
1%
b01111100 ,
1/
#2530000
0/
#2535000
0%
1/
#2540000
0/
#2545000
b01111101 $
1%
b01111101 ,
1/
#2550000
0/
#2555000
0%
1/
#2560000
0/
#2565000
b01111110 $
1%
b01111110 ,
1/
#2570000
0/
#2575000
0%
1/
#2580000
0/
#2585000
b01111111 $
1%
b01111111 ,
1/
#2590000
0/
#2595000
0%
1/
#2600000
0/
#2605000
b00000000000000000000000000000101 (
1/
#2610000
0/
#2615000
b10000000 $
1%
b10000000 ,
1.
1/
#2620000
0/
#2625000
0%
1/
#2630000
0/
#2635000
b00000000000000000000000000000111 (
1/
#2640000
0/
#2645000
1&
b00000001 +
0.
1/
#2650000
0/
#2655000
0&
1/
#2660000
0/
#2665000
1&
b00000010 +
1/
#2670000
0/
#2675000
0&
1/
#2680000
0/
#2685000
1&
b00000011 +
1/
#2690000
0/
#2695000
0&
1/
#2700000
0/
#2705000
1&
b00000100 +
1/
#2710000
0/
#2715000
0&
1/
#2720000
0/
#2725000
1&
b00000101 +
1/
#2730000
0/
#2735000
0&
1/
#2740000
0/
#2745000
1&
b00000110 +
1/
#2750000
0/
#2755000
0&
1/
#2760000
0/
#2765000
1&
b00000111 +
1/
#2770000
0/
#2775000
0&
1/
#2780000
0/
#2785000
1&
b00001000 +
1/
#2790000
0/
#2795000
0&
1/
#2800000
0/
#2805000
1&
b00001001 +
1/
#2810000
0/
#2815000
0&
1/
#2820000
0/
#2825000
1&
b00001010 +
1/
#2830000
0/
#2835000
0&
1/
#2840000
0/
#2845000
1&
b00001011 +
1/
#2850000
0/
#2855000
0&
1/
#2860000
0/
#2865000
1&
b00001100 +
1/
#2870000
0/
#2875000
0&
1/
#2880000
0/
#2885000
1&
b00001101 +
1/
#2890000
0/
#2895000
0&
1/
#2900000
0/
#2905000
1&
b00001110 +
1/
#2910000
0/
#2915000
0&
1/
#2920000
0/
#2925000
1&
b00001111 +
1/
#2930000
0/
#2935000
0&
1/
#2940000
0/
#2945000
1&
b00010000 +
1/
#2950000
0/
#2955000
0&
1/
#2960000
0/
#2965000
1&
b00010001 +
1/
#2970000
0/
#2975000
0&
1/
#2980000
0/
#2985000
1&
b00010010 +
1/
#2990000
0/
#2995000
0&
1/
#3000000
0/
#3005000
1&
b00010011 +
1/
#3010000
0/
#3015000
0&
1/
#3020000
0/
#3025000
1&
b00010100 +
1/
#3030000
0/
#3035000
0&
1/
#3040000
0/
#3045000
1&
b00010101 +
1/
#3050000
0/
#3055000
0&
1/
#3060000
0/
#3065000
1&
b00010110 +
1/
#3070000
0/
#3075000
0&
1/
#3080000
0/
#3085000
1&
b00010111 +
1/
#3090000
0/
#3095000
0&
1/
#3100000
0/
#3105000
1&
b00011000 +
1/
#3110000
0/
#3115000
0&
1/
#3120000
0/
#3125000
1&
b00011001 +
1/
#3130000
0/
#3135000
0&
1/
#3140000
0/
#3145000
1&
b00011010 +
1/
#3150000
0/
#3155000
0&
1/
#3160000
0/
#3165000
1&
b00011011 +
1/
#3170000
0/
#3175000
0&
1/
#3180000
0/
#3185000
1&
b00011100 +
1/
#3190000
0/
#3195000
0&
1/
#3200000
0/
#3205000
1&
b00011101 +
1/
#3210000
0/
#3215000
0&
1/
#3220000
0/
#3225000
1&
b00011110 +
1/
#3230000
0/
#3235000
0&
1/
#3240000
0/
#3245000
1&
b00011111 +
1/
#3250000
0/
#3255000
0&
1/
#3260000
0/
#3265000
1&
b00100000 +
1/
#3270000
0/
#3275000
0&
1/
#3280000
0/
#3285000
1&
b00100001 +
1/
#3290000
0/
#3295000
0&
1/
#3300000
0/
#3305000
1&
b00100010 +
1/
#3310000
0/
#3315000
0&
1/
#3320000
0/
#3325000
1&
b00100011 +
1/
#3330000
0/
#3335000
0&
1/
#3340000
0/
#3345000
1&
b00100100 +
1/
#3350000
0/
#3355000
0&
1/
#3360000
0/
#3365000
1&
b00100101 +
1/
#3370000
0/
#3375000
0&
1/
#3380000
0/
#3385000
1&
b00100110 +
1/
#3390000
0/
#3395000
0&
1/
#3400000
0/
#3405000
1&
b00100111 +
1/
#3410000
0/
#3415000
0&
1/
#3420000
0/
#3425000
1&
b00101000 +
1/
#3430000
0/
#3435000
0&
1/
#3440000
0/
#3445000
1&
b00101001 +
1/
#3450000
0/
#3455000
0&
1/
#3460000
0/
#3465000
1&
b00101010 +
1/
#3470000
0/
#3475000
0&
1/
#3480000
0/
#3485000
1&
b00101011 +
1/
#3490000
0/
#3495000
0&
1/
#3500000
0/
#3505000
1&
b00101100 +
1/
#3510000
0/
#3515000
0&
1/
#3520000
0/
#3525000
1&
b00101101 +
1/
#3530000
0/
#3535000
0&
1/
#3540000
0/
#3545000
1&
b00101110 +
1/
#3550000
0/
#3555000
0&
1/
#3560000
0/
#3565000
1&
b00101111 +
1/
#3570000
0/
#3575000
0&
1/
#3580000
0/
#3585000
1&
b00110000 +
1/
#3590000
0/
#3595000
0&
1/
#3600000
0/
#3605000
1&
b00110001 +
1/
#3610000
0/
#3615000
0&
1/
#3620000
0/
#3625000
1&
b00110010 +
1/
#3630000
0/
#3635000
0&
1/
#3640000
0/
#3645000
1&
b00110011 +
1/
#3650000
0/
#3655000
0&
1/
#3660000
0/
#3665000
1&
b00110100 +
1/
#3670000
0/
#3675000
0&
1/
#3680000
0/
#3685000
1&
b00110101 +
1/
#3690000
0/
#3695000
0&
1/
#3700000
0/
#3705000
1&
b00110110 +
1/
#3710000
0/
#3715000
0&
1/
#3720000
0/
#3725000
1&
b00110111 +
1/
#3730000
0/
#3735000
0&
1/
#3740000
0/
#3745000
1&
b00111000 +
1/
#3750000
0/
#3755000
0&
1/
#3760000
0/
#3765000
1&
b00111001 +
1/
#3770000
0/
#3775000
0&
1/
#3780000
0/
#3785000
1&
b00111010 +
1/
#3790000
0/
#3795000
0&
1/
#3800000
0/
#3805000
1&
b00111011 +
1/
#3810000
0/
#3815000
0&
1/
#3820000
0/
#3825000
1&
b00111100 +
1/
#3830000
0/
#3835000
0&
1/
#3840000
0/
#3845000
1&
b00111101 +
1/
#3850000
0/
#3855000
0&
1/
#3860000
0/
#3865000
1&
b00111110 +
1/
#3870000
0/
#3875000
0&
1/
#3880000
0/
#3885000
1&
b00111111 +
1/
#3890000
0/
#3895000
0&
1/
#3900000
0/
#3905000
1&
b01000000 +
1/
#3910000
0/
#3915000
0&
1/
#3920000
0/
#3925000
b00000000000000000000000000001000 (
1/
#3930000
0/
#3935000
b10000001 $
1%
b10000001 ,
1/
#3940000
0/
#3945000
0%
1/
#3950000
0/
#3955000
b10000010 $
1%
b10000010 ,
1/
#3960000
0/
#3965000
0%
1/
#3970000
0/
#3975000
b10000011 $
1%
b10000011 ,
1/
#3980000
0/
#3985000
0%
1/
#3990000
0/
#3995000
b10000100 $
1%
b10000100 ,
1/
#4000000
0/
#4005000
0%
1/
#4010000
0/
#4015000
b10000101 $
1%
b10000101 ,
1/
#4020000
0/
#4025000
0%
1/
#4030000
0/
#4035000
b10000110 $
1%
b10000110 ,
1/
#4040000
0/
#4045000
0%
1/
#4050000
0/
#4055000
b10000111 $
1%
b10000111 ,
1/
#4060000
0/
#4065000
0%
1/
#4070000
0/
#4075000
b10001000 $
1%
b10001000 ,
1/
#4080000
0/
#4085000
0%
1/
#4090000
0/
#4095000
b10001001 $
1%
b10001001 ,
1/
#4100000
0/
#4105000
0%
1/
#4110000
0/
#4115000
b10001010 $
1%
b10001010 ,
1/
